README.md
setup.py
fintool/__init__.py
fintool/nlptools.py
fintool/utils.py
fintool.egg-info/PKG-INFO
fintool.egg-info/SOURCES.txt
fintool.egg-info/dependency_links.txt
fintool.egg-info/entry_points.txt
fintool.egg-info/requires.txt
fintool.egg-info/top_level.txt