Metadata-Version: 2.1
Name: fintool
Version: 1.0.2
Summary: All-in-one tools for financial analysis
Home-page: https://github.com/YoshioYamauchi/financialtoolkit
Author: Yoshio Yamauchi == SPARKLE
Author-email: sparkle.official.01@gmail.com
License: MIT
Keywords: pandas,finance,pandas datareader
Platform: any
Requires-Python: >=3.6
